json_autocomplete-0.2.5.dist-info/top_level.txt
json_autocomplete-0.2.5.dist-info/RECORD
json_autocomplete-0.2.5.dist-info/METADATA
json_autocomplete-0.2.5.dist-info/WHEEL
json_autocomplete/json_autocomplete.pyi
json_autocomplete/json_autocomplete.pyx
json_autocomplete/json.h
json_autocomplete/__init__.py
json_autocomplete/json_autocomplete.cpython-39-x86_64-linux-gnu.so
json_autocomplete/json.cpp
json_autocomplete/json_autocomplete.cpp
json_autocomplete.libs/libstdc++-496613c0.so.6.0.32
json_autocomplete.libs/libgcc_s-a3a07607.so.1
